hc_mcp_aws/__init__.py
hc_mcp_aws/__main__.py
hc_mcp_aws/cloudwatch.py
hc_mcp_aws/common.py
hc_mcp_aws/organization.py
hc_mcp_aws/resource_discovery.py
hc_mcp_aws/resource_discovery_helpers.py
hc_mcp_aws/security.py
hc_mcp_aws/server.py
hc_mcp_aws/waf.py
hc_mcp_aws/discovery/__init__.py
hc_mcp_aws/discovery/apigateway_discovery.py
hc_mcp_aws/discovery/cloudfront_discovery.py
hc_mcp_aws/discovery/cloudwatch_discovery.py
hc_mcp_aws/discovery/dynamodb_discovery.py
hc_mcp_aws/discovery/ec2_discovery.py
hc_mcp_aws/discovery/iam_discovery.py
hc_mcp_aws/discovery/inspector_discovery.py
hc_mcp_aws/discovery/lambda_discovery.py
hc_mcp_aws/discovery/rds_discovery.py
hc_mcp_aws/discovery/route53_discovery.py
hc_mcp_aws/discovery/s3_discovery.py
hc_mcp_aws/discovery/securityhub_discovery.py
hc_mcp_aws/discovery/sns_discovery.py
hc_mcp_aws/discovery/sqs_discovery.py
hc_mcp_aws/discovery/vpc_discovery.py
hc_mcp_aws/discovery/waf_discovery.py
hc_mcp_aws-2025.4.10.dist-info/METADATA
hc_mcp_aws-2025.4.10.dist-info/WHEEL
hc_mcp_aws-2025.4.10.dist-info/entry_points.txt
hc_mcp_aws-2025.4.10.dist-info/RECORD
