Metadata-Version: 2.4
Name: hc-mcp-aws
Version: 2025.4.10
Summary: HC MCP server for AWS monitoring and management
Author-email: Erik Meinders <erik@easytocloud.com>
Requires-Python: >=3.10
Requires-Dist: boto3>=1.28.0
Requires-Dist: mcp-config-manager>=0.1.1
Requires-Dist: mcp>=1.2.0
Requires-Dist: pydantic>=2.0.0
Requires-Dist: typing-extensions>=4.0.0
